china_calendar/__init__.py
china_calendar/calendar_util.py
china_calendar/version.py
tests/__init__.py
tests/china_calendar_test.py
china_calendar-1.0.1.dist-info/METADATA
china_calendar-1.0.1.dist-info/WHEEL
china_calendar-1.0.1.dist-info/top_level.txt
china_calendar-1.0.1.dist-info/zip-safe
china_calendar-1.0.1.dist-info/RECORD
